tkmsgcat/__init__.py
tkinter_msgcat-0.1.0.dist-info/LICENSE
tkinter_msgcat-0.1.0.dist-info/METADATA
tkinter_msgcat-0.1.0.dist-info/WHEEL
tkinter_msgcat-0.1.0.dist-info/top_level.txt
tkinter_msgcat-0.1.0.dist-info/RECORD
