Metadata-Version: 2.1
Name: tkinter-msgcat
Version: 0.1.0
Summary: Create multilingual interfaces for your tkinter applications
Home-page: https://github.com/demberto/tkinter-msgcat
Author: demberto
Author-email: demberto@protonmail.com
License: BSD-3-Clause
Keywords: i18n, tkinter, msgcat
Platform: UNKNOWN
Classifier: License :: OSI Approved :: BSD License
Classifier: Programming Language :: Python :: 3
Classifier: Programming Language :: Python :: 3 :: Only
Classifier: Programming Language :: Python :: 3.7
Classifier: Programming Language :: Python :: 3.8
Classifier: Programming Language :: Python :: 3.9
Classifier: Programming Language :: Python :: 3.10
Requires-Python: >=3.7
License-File: LICENSE
